fixture/__init__.py
fixture/base/__init__.py
fixture/base/con_mysql.py
fixture/operate/__init__.py
fixture/operate/operator.py
fixture/worker/__init__.py
fixture/worker/worker.py
fixtureMr/__init__.py
fixtureMr/base/__init__.py
fixtureMr/base/con_mysql.py
fixtureMr/base/http_request.py
fixtureMr/base/send_email.py
fixtureMr/operate/__init__.py
fixtureMr/operate/operator.py
fixtureMr/worker/__init__.py
fixtureMr/worker/worker.py
fixtureMr-1.4.0.dist-info/METADATA
fixtureMr-1.4.0.dist-info/WHEEL
fixtureMr-1.4.0.dist-info/top_level.txt
fixtureMr-1.4.0.dist-info/RECORD
